{
  "environment": "web",
  "format": "html",
  "prefix": "https://storage.googleapis.com",
  "mainga": "UA-49880327-14",
  "updated": "2021-11-17T10:55:47+01:00",
  "id": "bios-1",
  "duration": 10,
  "title": "Protección de la BIOS/UEFI",
  "summary": "bastionado bios",
  "source": "C:\\Users\\Usuario\\Documents\\bios1\\codelab-bios1.1.md",
  "theme": "",
  "status": [
    "published"
  ],
  "category": [
    "codelab",
    "markdown"
  ],
  "tags": [
    "web"
  ],
  "feedback": "https://github.com/Igonbot/bastionado/issues",
  "url": "bios-1"
}
